webtemplate_dbca-1.8.3.dist-info/METADATA
webtemplate_dbca-1.8.3.dist-info/WHEEL
webtemplate_dbca-1.8.3.dist-info/entry_points.txt
webtemplate_dbca-1.8.3.dist-info/licenses/LICENSE
webtemplate_dbca/__init__.py
webtemplate_dbca/static/css/dbca-custom.css
webtemplate_dbca/static/favicon.ico
webtemplate_dbca/static/img/dbca_logo_sml.png
webtemplate_dbca/static/img/dpaw_logo_small.png
webtemplate_dbca/static/img/logo-dpaw.gif
webtemplate_dbca/static/img/top-bg.gif
webtemplate_dbca/static/img/waTextBlack_80-bluebg.gif
webtemplate_dbca/static/js/vendor/modernizr-3.11.7.min.js
webtemplate_dbca/templates/webtemplate_dbca/base_b4.html
webtemplate_dbca/templates/webtemplate_dbca/base_b5.html
webtemplate_dbca/templates/webtemplate_dbca/logged_out.html
webtemplate_dbca/templates/webtemplate_dbca/login.html
webtemplate_dbca-1.8.3.dist-info/RECORD
