Metadata-Version: 2.4
Name: webtemplate-dbca
Version: 1.8.3
Summary: Base HTML templates for DBCA Django projects
Author-Email: Ashley Felton <ashley.felton@dbca.wa.gov.au>
License-Expression: Apache-2.0
Classifier: Framework :: Django
Classifier: Framework :: Django :: 3.2
Classifier: Framework :: Django :: 4.0
Classifier: Framework :: Django :: 4.2
Classifier: Framework :: Django :: 5.0
Classifier: Framework :: Django :: 5.2
Classifier: Environment :: Web Environment
Classifier: Intended Audience :: Developers
Classifier: Development Status :: 5 - Production/Stable
Classifier: Programming Language :: Python
Classifier: Programming Language :: Python :: 3
Classifier: Programming Language :: Python :: 3.9
Classifier: Programming Language :: Python :: 3.10
Classifier: Programming Language :: Python :: 3.11
Classifier: Programming Language :: Python :: 3.12
Classifier: Programming Language :: Python :: 3.13
Classifier: Topic :: Software Development :: Libraries
Classifier: Topic :: Software Development :: Libraries :: Python Modules
Project-URL: Homepage, https://github.com/dbca-wa/webtemplate
Project-URL: Repository, https://github.com/dbca-wa/webtemplate.git
Project-URL: Changelog, https://github.com/dbca-wa/webtemplate/blob/master/CHANGELOG.md
Project-URL: GitHub, https://github.com/dbca-wa/webtemplate
Requires-Python: <4.0,>=3.9
Requires-Dist: django<6,>=3.2
